{
    "name": "Global Information",
    "numberOfRequests": {
        "total": 129,
        "ok": 129,
        "ko": 0
    },
    "minResponseTime": {
        "total": 60,
        "ok": 60,
        "ko": 0
    },
    "maxResponseTime": {
        "total": 219,
        "ok": 219,
        "ko": 0
    },
    "meanResponseTime": {
        "total": 84,
        "ok": 84,
        "ko": 0
    },
    "standardDeviation": {
        "total": 23,
        "ok": 23,
        "ko": 0
    },
    "percentiles1": {
        "total": 78,
        "ok": 78,
        "ko": 0
    },
    "percentiles2": {
        "total": 84,
        "ok": 84,
        "ko": 0
    },
    "percentiles3": {
        "total": 114,
        "ok": 114,
        "ko": 0
    },
    "percentiles4": {
        "total": 197,
        "ok": 197,
        "ko": 0
    },
    "group1": {
    "name": "t < 800 ms",
    "count": 129,
    "percentage": 100
},
    "group2": {
    "name": "800 ms < t < 1200 ms",
    "count": 0,
    "percentage": 0
},
    "group3": {
    "name": "t > 1200 ms",
    "count": 0,
    "percentage": 0
},
    "group4": {
    "name": "failed",
    "count": 0,
    "percentage": 0
},
    "meanNumberOfRequestsPerSecond": {
        "total": 8.6,
        "ok": 8.6,
        "ko": 0
    }
}